linear_regression/__init__.py
linear_regression/lr.py
linear_regression-0.1.dist-info/DESCRIPTION.rst
linear_regression-0.1.dist-info/METADATA
linear_regression-0.1.dist-info/RECORD
linear_regression-0.1.dist-info/WHEEL
linear_regression-0.1.dist-info/metadata.json
linear_regression-0.1.dist-info/top_level.txt
